setup.py
nicks_dominic_distributions_probability.egg-info/PKG-INFO
nicks_dominic_distributions_probability.egg-info/SOURCES.txt
nicks_dominic_distributions_probability.egg-info/dependency_links.txt
nicks_dominic_distributions_probability.egg-info/not-zip-safe
nicks_dominic_distributions_probability.egg-info/top_level.txt
nicks_dsnd_probability/Binomialdistribution_challenge.py
nicks_dsnd_probability/Gaussiandistribution.py
nicks_dsnd_probability/Generaldistribution.py
nicks_dsnd_probability/__init__.py