Metadata-Version: 2.1
Name: nicks-dominic-distributions-probability
Version: 1.1
Summary: Guassian and Binomial Distributions
Home-page: UNKNOWN
Author: Nicholas Smith
Author-email: nicholas122008@hotmail.com
License: UNKNOWN
Platform: UNKNOWN
